puavro/__init__.py
puavro/puavro.py
puavro-1.0.3.dist-info/LICENSE
puavro-1.0.3.dist-info/METADATA
puavro-1.0.3.dist-info/WHEEL
puavro-1.0.3.dist-info/top_level.txt
puavro-1.0.3.dist-info/RECORD
