Metadata-Version: 2.1
Name: puavro
Version: 1.0.3
Summary: Pulsar AVRO interface allowing to read/write AVRO messages from/to dict
Home-page: https://github.com/bry00/puavro
Author: Bartek Rybak
License: MIT
Keywords: pulsar avro
Platform: UNKNOWN
Classifier: Programming Language :: Python :: 3.8
Classifier: Programming Language :: Python :: 3.9
Requires-Python: >=3.8
Requires-Dist: fastavro (>=1.4.4)
Requires-Dist: pulsar-client (>=2.7.0)
